sisou.py
config/__init__.py
config/config.toml.default
modules/WindowsConsumerDownload.py
modules/__init__.py
modules/exceptions.py
modules/utils.py
modules/updaters/ArchLinux.py
modules/updaters/ChromeOS.py
modules/updaters/Clonezilla.py
modules/updaters/Debian.py
modules/updaters/Fedora.py
modules/updaters/FreeDOS.py
modules/updaters/GPartedLive.py
modules/updaters/GenericUpdater.py
modules/updaters/HDAT2.py
modules/updaters/HirensBootCDPE.py
modules/updaters/KaliLinux.py
modules/updaters/LinuxMint.py
modules/updaters/Manjaro.py
modules/updaters/MemTest86Plus.py
modules/updaters/OPNsense.py
modules/updaters/OpenSUSE.py
modules/updaters/OpenSUSERolling.py
modules/updaters/Proxmox.py
modules/updaters/Rescuezilla.py
modules/updaters/RockyLinux.py
modules/updaters/ShredOS.py
modules/updaters/SuperGrub2.py
modules/updaters/SystemRescue.py
modules/updaters/Tails.py
modules/updaters/TempleOS.py
modules/updaters/TrueNAS.py
modules/updaters/Ubuntu.py
modules/updaters/UltimateBootCD.py
modules/updaters/Windows10.py
modules/updaters/Windows11.py
modules/updaters/__init__.py
modules/updaters/util_update_checker.py
sisou-1.4.1.dist-info/licenses/LICENSE
sisou-1.4.1.dist-info/METADATA
sisou-1.4.1.dist-info/WHEEL
sisou-1.4.1.dist-info/entry_points.txt
sisou-1.4.1.dist-info/top_level.txt
sisou-1.4.1.dist-info/RECORD
