Metadata-Version: 2.4
Name: sisou
Version: 1.4.1
Summary: A powerful tool to conveniently update all of your ISO files!
Home-page: https://github.com/JoshuaVandaele/SuperISOUpdater
Author: Joshua Vandaele
Author-email: joshua@vandaele.software
Project-URL: Bug Reports, https://github.com/JoshuaVandaele/SuperISOUpdater/issues
Project-URL: Source, https://github.com/JoshuaVandaele/SuperISOUpdater/
Keywords: ventoy,updater,os,iso,updater,sisou,cli
Classifier: Development Status :: 5 - Production/Stable
Classifier: Intended Audience :: End Users/Desktop
Classifier: Topic :: Internet
Classifier: License :: OSI Approved :: GNU General Public License v3 (GPLv3)
Classifier: Programming Language :: Python :: 3.10
Classifier: Programming Language :: Python :: 3.11
Classifier: Programming Language :: Python :: 3.12
Classifier: Programming Language :: Python :: 3.13
Classifier: Programming Language :: Python :: 3 :: Only
Requires-Python: >=3.10, <4
License-File: LICENSE
Requires-Dist: beautifulsoup4==4.12.2
Requires-Dist: requests==2.31.0
Requires-Dist: tqdm==4.65.0
Requires-Dist: PGPy13==0.6.1rc1
Dynamic: author
Dynamic: author-email
Dynamic: classifier
Dynamic: description
Dynamic: description-content-type
Dynamic: home-page
Dynamic: keywords
Dynamic: license-file
Dynamic: project-url
Dynamic: requires-dist
Dynamic: requires-python
Dynamic: summary
